emulator2df/README.MD
emulator2df/__init__.py
emulator2df/requirements.txt
emulator2df/thirdparty.json
emulator2df-0.10.dist-info/LICENSE.rst
emulator2df-0.10.dist-info/METADATA
emulator2df-0.10.dist-info/WHEEL
emulator2df-0.10.dist-info/top_level.txt
emulator2df-0.10.dist-info/RECORD
