Metadata-Version: 2.1
Name: emulator2df
Version: 0.10
Summary: Android emulators to DataFrame
Home-page: https://github.com/hansalemaos/emulator2df
Author: Johannes Fischer
Author-email: aulasparticularesdealemaosp@gmail.com
License: MIT
Keywords: android
Classifier: Development Status :: 4 - Beta
Classifier: Programming Language :: Python :: 3 :: Only
Classifier: Programming Language :: Python :: 3.10
Classifier: Topic :: Software Development :: Libraries :: Python Modules
Classifier: Topic :: Utilities
License-File: LICENSE.rst
Requires-Dist: pandas
Requires-Dist: psutil
